{
  "$schema": "https://raw.githubusercontent.com/spdx/spdx-spec/v2.2.1/schemas/spdx-schema.json",
  "spdxVersion": "SPDX-2.2",
  "dataLicense": "CC0-1.0",
  "SPDXID": "SPDXRef-DOCUMENT",
  "documentNamespace": "https://spdx.org/spdxdocs/boost-lambda-x64-windows-1.78.0-2814fb9f-4b7b-4452-b507-88bf87f8b841",
  "name": "boost-lambda:x64-windows@1.78.0 d23f0d790eea84758db73f7b27bad6a8260746d57762d0f786a65eea7102f8e0",
  "creationInfo": {
    "creators": [
      "Tool: vcpkg-2024-08-01-fd884a0d390d12783076341bd43d77c3a6a15658"
    ],
    "created": "2024-09-05T08:59:46Z"
  },
  "relationships": [
    {
      "spdxElementId": "SPDXRef-port",
      "relationshipType": "GENERATES",
      "relatedSpdxElement": "SPDXRef-binary"
    },
    {
      "spdxElementId": "SPDXRef-port",
      "relationshipType": "CONTAINS",
      "relatedSpdxElement": "SPDXRef-file-0"
    },
    {
      "spdxElementId": "SPDXRef-port",
      "relationshipType": "CONTAINS",
      "relatedSpdxElement": "SPDXRef-file-1"
    },
    {
      "spdxElementId": "SPDXRef-binary",
      "relationshipType": "GENERATED_FROM",
      "relatedSpdxElement": "SPDXRef-port"
    },
    {
      "spdxElementId": "SPDXRef-file-0",
      "relationshipType": "CONTAINED_BY",
      "relatedSpdxElement": "SPDXRef-port"
    },
    {
      "spdxElementId": "SPDXRef-file-1",
      "relationshipType": "CONTAINED_BY",
      "relatedSpdxElement": "SPDXRef-port"
    }
  ],
  "packages": [
    {
      "name": "boost-lambda",
      "SPDXID": "SPDXRef-port",
      "versionInfo": "1.78.0",
      "downloadLocation": "git+https://github.com/Microsoft/vcpkg@ad7994962fa2139e8b2e67adbf505c555a57f3c6",
      "homepage": "https://github.com/boostorg/lambda",
      "licenseConcluded": "NOASSERTION",
      "licenseDeclared": "NOASSERTION",
      "copyrightText": "NOASSERTION",
      "description": "Boost lambda module",
      "comment": "This is the port (recipe) consumed by vcpkg."
    },
    {
      "name": "boost-lambda:x64-windows",
      "SPDXID": "SPDXRef-binary",
      "versionInfo": "d23f0d790eea84758db73f7b27bad6a8260746d57762d0f786a65eea7102f8e0",
      "downloadLocation": "NONE",
      "licenseConcluded": "NOASSERTION",
      "licenseDeclared": "NOASSERTION",
      "copyrightText": "NOASSERTION",
      "comment": "This is a binary package built by vcpkg."
    },
    {
      "SPDXID": "SPDXRef-resource-1",
      "name": "boostorg/lambda",
      "downloadLocation": "git+https://github.com/boostorg/lambda@boost-1.78.0",
      "licenseConcluded": "NOASSERTION",
      "licenseDeclared": "NOASSERTION",
      "copyrightText": "NOASSERTION",
      "checksums": [
        {
          "algorithm": "SHA512",
          "checksumValue": "b3d923435133ba4bcffd0fb722d92ccf4f7b739a51390319db10ac43452141c1d786755ae143149102324548d4beb7e87e5767381b93cc814593ce9123f2dffb"
        }
      ]
    }
  ],
  "files": [
    {
      "fileName": "./D:/projects/vcpkg/buildtrees/versioning_/versions/boost-lambda/ad7994962fa2139e8b2e67adbf505c555a57f3c6/portfile.cmake",
      "SPDXID": "SPDXRef-file-0",
      "checksums": [
        {
          "algorithm": "SHA256",
          "checksumValue": "97fca2aa1eda8f4edbe0856672b844e56ce6c9a1445c6501ee5eb68c6899aad5"
        }
      ],
      "licenseConcluded": "NOASSERTION",
      "copyrightText": "NOASSERTION"
    },
    {
      "fileName": "./D:/projects/vcpkg/buildtrees/versioning_/versions/boost-lambda/ad7994962fa2139e8b2e67adbf505c555a57f3c6/vcpkg.json",
      "SPDXID": "SPDXRef-file-1",
      "checksums": [
        {
          "algorithm": "SHA256",
          "checksumValue": "8b0a10980d3bd520e3a1948e27f291cea1edc6187786d9e29fae2a855d8123f9"
        }
      ],
      "licenseConcluded": "NOASSERTION",
      "copyrightText": "NOASSERTION"
    }
  ]
}
