{
  "$schema": "https://raw.githubusercontent.com/spdx/spdx-spec/v2.2.1/schemas/spdx-schema.json",
  "spdxVersion": "SPDX-2.2",
  "dataLicense": "CC0-1.0",
  "SPDXID": "SPDXRef-DOCUMENT",
  "documentNamespace": "https://spdx.org/spdxdocs/boost-circular-buffer-x64-windows-1.78.0-6532a10e-fa28-4b5a-bf2a-09b9a5610ecf",
  "name": "boost-circular-buffer:x64-windows@1.78.0 848bef86430accf26b896b3efb87bd2f4ace2f22de4cf9ea5b6899e7816a9643",
  "creationInfo": {
    "creators": [
      "Tool: vcpkg-2024-08-01-fd884a0d390d12783076341bd43d77c3a6a15658"
    ],
    "created": "2024-09-05T08:48:59Z"
  },
  "relationships": [
    {
      "spdxElementId": "SPDXRef-port",
      "relationshipType": "GENERATES",
      "relatedSpdxElement": "SPDXRef-binary"
    },
    {
      "spdxElementId": "SPDXRef-port",
      "relationshipType": "CONTAINS",
      "relatedSpdxElement": "SPDXRef-file-0"
    },
    {
      "spdxElementId": "SPDXRef-port",
      "relationshipType": "CONTAINS",
      "relatedSpdxElement": "SPDXRef-file-1"
    },
    {
      "spdxElementId": "SPDXRef-binary",
      "relationshipType": "GENERATED_FROM",
      "relatedSpdxElement": "SPDXRef-port"
    },
    {
      "spdxElementId": "SPDXRef-file-0",
      "relationshipType": "CONTAINED_BY",
      "relatedSpdxElement": "SPDXRef-port"
    },
    {
      "spdxElementId": "SPDXRef-file-1",
      "relationshipType": "CONTAINED_BY",
      "relatedSpdxElement": "SPDXRef-port"
    }
  ],
  "packages": [
    {
      "name": "boost-circular-buffer",
      "SPDXID": "SPDXRef-port",
      "versionInfo": "1.78.0",
      "downloadLocation": "git+https://github.com/Microsoft/vcpkg@239a4eff939919bbabf11914dbb656992e4e26ae",
      "homepage": "https://github.com/boostorg/circular_buffer",
      "licenseConcluded": "NOASSERTION",
      "licenseDeclared": "NOASSERTION",
      "copyrightText": "NOASSERTION",
      "description": "Boost circular_buffer module",
      "comment": "This is the port (recipe) consumed by vcpkg."
    },
    {
      "name": "boost-circular-buffer:x64-windows",
      "SPDXID": "SPDXRef-binary",
      "versionInfo": "848bef86430accf26b896b3efb87bd2f4ace2f22de4cf9ea5b6899e7816a9643",
      "downloadLocation": "NONE",
      "licenseConcluded": "NOASSERTION",
      "licenseDeclared": "NOASSERTION",
      "copyrightText": "NOASSERTION",
      "comment": "This is a binary package built by vcpkg."
    },
    {
      "SPDXID": "SPDXRef-resource-1",
      "name": "boostorg/circular_buffer",
      "downloadLocation": "git+https://github.com/boostorg/circular_buffer@boost-1.78.0",
      "licenseConcluded": "NOASSERTION",
      "licenseDeclared": "NOASSERTION",
      "copyrightText": "NOASSERTION",
      "checksums": [
        {
          "algorithm": "SHA512",
          "checksumValue": "07b8cbec9a4f50b06c7da5ca496c86d697d8c78fb36588a9d6b36e9042ca53d2c28a0bb6cd97904a049efe60990b81d45b14693bffc91133dde4ab253deb0ea1"
        }
      ]
    }
  ],
  "files": [
    {
      "fileName": "./D:/projects/vcpkg/buildtrees/versioning_/versions/boost-circular-buffer/239a4eff939919bbabf11914dbb656992e4e26ae/portfile.cmake",
      "SPDXID": "SPDXRef-file-0",
      "checksums": [
        {
          "algorithm": "SHA256",
          "checksumValue": "68cd1796c9f5ff5095b2d5ecb65316c58cf4c2e1b1e2f1eb86070ecc73cc43ca"
        }
      ],
      "licenseConcluded": "NOASSERTION",
      "copyrightText": "NOASSERTION"
    },
    {
      "fileName": "./D:/projects/vcpkg/buildtrees/versioning_/versions/boost-circular-buffer/239a4eff939919bbabf11914dbb656992e4e26ae/vcpkg.json",
      "SPDXID": "SPDXRef-file-1",
      "checksums": [
        {
          "algorithm": "SHA256",
          "checksumValue": "906f94e63cfa33ad6c2e1c8aa116f8265f13a988ae2b98d0d34d0f356d51d08e"
        }
      ],
      "licenseConcluded": "NOASSERTION",
      "copyrightText": "NOASSERTION"
    }
  ]
}
